README.txt
setup.cfg
setup.py
docs/HISTORY.txt
docs/INSTALL.txt
docs/LICENSE.GPL
docs/LICENSE.txt
docs/API/api-objects.txt
docs/API/class-tree.html
docs/API/crarr.png
docs/API/epydoc.css
docs/API/epydoc.js
docs/API/frames.html
docs/API/help.html
docs/API/identifier-index.html
docs/API/index.html
docs/API/module-tree.html
docs/API/platecom.langview-module.html
docs/API/platecom.langview-pysrc.html
docs/API/platecom.langview.Extensions-module.html
docs/API/platecom.langview.Extensions-pysrc.html
docs/API/platecom.langview.Extensions.install-module.html
docs/API/platecom.langview.Extensions.install-pysrc.html
docs/API/platecom.langview.browser-module.html
docs/API/platecom.langview.browser-pysrc.html
docs/API/platecom.langview.browser.admin-module.html
docs/API/platecom.langview.browser.admin-pysrc.html
docs/API/platecom.langview.browser.views-module.html
docs/API/platecom.langview.browser.views-pysrc.html
docs/API/platecom.langview.browser.views.FixedLanguage-class.html
docs/API/platecom.langview.browser.views.MultiLanguages-class.html
docs/API/platecom.langview.config-module.html
docs/API/platecom.langview.config-pysrc.html
docs/API/platecom.langview.events-module.html
docs/API/platecom.langview.events-pysrc.html
docs/API/platecom.langview.exportimport-module.html
docs/API/platecom.langview.exportimport-pysrc.html
docs/API/platecom.langview.exportimport.propertiestool-module.html
docs/API/platecom.langview.exportimport.propertiestool-pysrc.html
docs/API/platecom.langview.exportimport.propertiestool.SimpleItemWithPropertiesXMLAdapter-class.html
docs/API/platecom.langview.interfaces-module.html
docs/API/platecom.langview.interfaces-pysrc.html
docs/API/platecom.langview.interfaces.IMemberDataTool-class.html
docs/API/platecom.langview.interfaces.IPartialTranslated-class.html
docs/API/platecom.langview.setuphandlers-module.html
docs/API/platecom.langview.setuphandlers-pysrc.html
docs/API/platecom.langview.tests-module.html
docs/API/platecom.langview.tests-pysrc.html
icsemantic.langfallback.egg-info/PKG-INFO
icsemantic.langfallback.egg-info/SOURCES.txt
icsemantic.langfallback.egg-info/dependency_links.txt
icsemantic.langfallback.egg-info/entry_points.txt
icsemantic.langfallback.egg-info/namespace_packages.txt
icsemantic.langfallback.egg-info/not-zip-safe
icsemantic.langfallback.egg-info/requires.txt
icsemantic.langfallback.egg-info/top_level.txt
