Metadata-Version: 1.0
Name: icsemantic.langfallback
Version: 1.0-dev-r371
Summary: icSemantic.LangFallback
Home-page: http://www.platecom.com/productos/icsemantic.langfallback/
Author: Inter-Cultura Consultora SRL - Ibai Sistemas SA - Eusko Ikaskuntza-Sociedad de Estudios Vascos
Author-email: dev@inter-cultura.com
License: GPL
Keywords: icsemantic,platecom,semantic,language,fallback,plone
Platform: UNKNOWN
Classifier: Topic :: Text Processing :: Linguistic
Classifier: Environment :: Web Environment
Classifier: Framework :: Plone
Classifier: Development Status :: 4 - Beta
Classifier: Intended Audience :: Information Technology
Classifier: License :: OSI Approved :: GNU General Public License (GPL)
Classifier: Operating System :: OS Independent
Classifier: Programming Language :: Python
